AgentOversight/__init__.py
AgentOversight/agent_logic.py
AgentOversight/app.py
AgentOversight/templates/index.html
agentoversight-0.1.0.dist-info/LICENSE
agentoversight-0.1.0.dist-info/METADATA
agentoversight-0.1.0.dist-info/WHEEL
agentoversight-0.1.0.dist-info/entry_points.txt
agentoversight-0.1.0.dist-info/top_level.txt
agentoversight-0.1.0.dist-info/RECORD
