Metadata-Version: 2.2
Name: AgentOversight
Version: 0.1.0
Summary: A tool to oversee and evaluate agentic AI performance with validation and guidance
Home-page: https://github.com/loks2cool/AgentOversight
Author: Logeswaran
Author-email: loks2cool@gmail.com
Classifier: Programming Language :: Python :: 3
Classifier: License :: OSI Approved :: MIT License
Classifier: Operating System :: OS Independent
Classifier: Intended Audience :: Developers
Classifier: Topic :: Software Development :: Libraries :: Python Modules
Classifier: Topic :: Scientific/Engineering :: Artificial Intelligence
Requires-Python: >=3.7
License-File: LICENSE
Requires-Dist: Flask>=2.3.3
Requires-Dist: nltk>=3.8.1
Requires-Dist: openai>=1.10.0
Requires-Dist: requests>=2.31.0
Requires-Dist: textblob>=0.18.0
Requires-Dist: httpx>=0.27.0
Dynamic: author
Dynamic: author-email
Dynamic: classifier
Dynamic: description
Dynamic: description-content-type
Dynamic: home-page
Dynamic: requires-dist
Dynamic: requires-python
Dynamic: summary
